gradio/.dockerignore
gradio/CHANGELOG.md
gradio/__init__.py
gradio/analytics.py
gradio/blocks.py
gradio/blocks_events.py
gradio/blocks_events.pyi
gradio/chat_interface.py
gradio/component_meta.py
gradio/context.py
gradio/data_classes.py
gradio/events.py
gradio/exceptions.py
gradio/external.py
gradio/external_utils.py
gradio/flagging.py
gradio/helpers.py
gradio/http_server.py
gradio/image_utils.py
gradio/interface.py
gradio/ipython_ext.py
gradio/monitoring_dashboard.py
gradio/networking.py
gradio/oauth.py
gradio/package.json
gradio/pipelines.py
gradio/pipelines_utils.py
gradio/processing_utils.py
gradio/queueing.py
gradio/ranged_response.py
gradio/renderable.py
gradio/route_utils.py
gradio/routes.py
gradio/server_messages.py
gradio/state_holder.py
gradio/strings.py
gradio/templates.py
gradio/templates.pyi
gradio/tunneling.py
gradio/utils.py
gradio/wasm_utils.py
gradio/_frontend_code/accordion/Index.svelte
gradio/_frontend_code/accordion/package.json
gradio/_frontend_code/accordion/shared/Accordion.svelte
gradio/_frontend_code/annotatedimage/Index.svelte
gradio/_frontend_code/annotatedimage/package.json
gradio/_frontend_code/atoms/package.json
gradio/_frontend_code/atoms/src/Block.svelte
gradio/_frontend_code/atoms/src/BlockLabel.svelte
gradio/_frontend_code/atoms/src/BlockTitle.svelte
gradio/_frontend_code/atoms/src/Empty.svelte
gradio/_frontend_code/atoms/src/IconButton.svelte
gradio/_frontend_code/atoms/src/Info.svelte
gradio/_frontend_code/atoms/src/SelectSource.svelte
gradio/_frontend_code/atoms/src/ShareButton.svelte
gradio/_frontend_code/atoms/src/Toolbar.svelte
gradio/_frontend_code/atoms/src/UploadText.svelte
gradio/_frontend_code/atoms/src/index.ts
gradio/_frontend_code/atoms/src/icons/clear.svg
gradio/_frontend_code/atoms/src/icons/edit.svg
gradio/_frontend_code/atoms/src/icons/file.svg
gradio/_frontend_code/audio/Example.svelte
gradio/_frontend_code/audio/Index.svelte
gradio/_frontend_code/audio/index.ts
gradio/_frontend_code/audio/package.json
gradio-4.38.0.dist-info/METADATA
gradio-4.38.0.dist-info/WHEEL
gradio-4.38.0.dist-info/entry_points.txt
gradio-4.38.0.dist-info/licenses/LICENSE
gradio-4.38.0.dist-info/RECORD
