Metadata-Version: 2.3
Name: gradio
Version: 4.38.0
Summary: Python library for easily interacting with trained machine learning models
Project-URL: Homepage, https://github.com/gradio-app/gradio
Author-email: Abubakar Abid <gradio-team@huggingface.co>, Ali Abid <gradio-team@huggingface.co>, Ali Abdalla <gradio-team@huggingface.co>, Dawood Khan <gradio-team@huggingface.co>, Ahsen Khaliq <gradio-team@huggingface.co>, Pete Allen <gradio-team@huggingface.co>, Ömer Faruk Özdemir <gradio-team@huggingface.co>, Freddy A Boulton <gradio-team@huggingface.co>, Hannah Blair <gradio-team@huggingface.co>
License-Expression: Apache-2.0
License-File: LICENSE
Keywords: machine learning,reproducibility,visualization
Classifier: Development Status :: 5 - Production/Stable
Classifier: License :: OSI Approved :: Apache Software License
Classifier: Operating System :: OS Independent
Classifier: Programming Language :: Python :: 3
Classifier: Programming Language :: Python :: 3 :: Only
Classifier: Programming Language :: Python :: 3.8
Classifier: Programming Language :: Python :: 3.9
Classifier: Programming Language :: Python :: 3.10
Classifier: Programming Language :: Python :: 3.11
Classifier: Topic :: Scientific/Engineering
Classifier: Topic :: Scientific/Engineering :: Artificial Intelligence
Classifier: Topic :: Scientific/Engineering :: Visualization
Requires-Python: >=3.8
Requires-Dist: aiofiles<24.0,>=22.0
Requires-Dist: altair<6.0,>=5.0
Requires-Dist: fastapi
Requires-Dist: ffmpy
Requires-Dist: gradio-client==1.1.0
Requires-Dist: httpx>=0.24.1
Requires-Dist: huggingface-hub>=0.19.3
Requires-Dist: importlib-resources<7.0,>=1.3
Requires-Dist: jinja2<4.0
Requires-Dist: markupsafe~=2.0
Requires-Dist: matplotlib~=3.0
Requires-Dist: numpy<3.0,>=1.0
Requires-Dist: orjson~=3.0
Requires-Dist: packaging
Requires-Dist: pandas<3.0,>=1.0
Requires-Dist: pillow<11.0,>=8.0
Requires-Dist: pydantic>=2.0
Requires-Dist: pydub
Requires-Dist: python-multipart>=0.0.9
Requires-Dist: pyyaml<7.0,>=5.0
Requires-Dist: ruff>=0.2.2; sys_platform != 'emscripten'
Requires-Dist: semantic-version~=2.0
Requires-Dist: tomlkit==0.12.0
Requires-Dist: typer<1.0,>=0.12; sys_platform != 'emscripten'
Requires-Dist: typing-extensions~=4.0
Requires-Dist: urllib3~=2.0
Requires-Dist: uvicorn>=0.14.0; sys_platform != 'emscripten'
Provides-Extra: oauth
Requires-Dist: authlib; extra == 'oauth'
Requires-Dist: itsdangerous; extra == 'oauth'
